easy_nlp_translate/__init__.py
easy_nlp_translate/config.py
easy_nlp_translate/exceptions.py
easy_nlp_translate/huggingface_translator_base.py
easy_nlp_translate/initialize.py
easy_nlp_translate/llm_translator_base.py
easy_nlp_translate/prompt_config.py
easy_nlp_translate/translator_base.py
easy_nlp_translate/huggingface_models/__init__.py
easy_nlp_translate/huggingface_models/mbart.py
easy_nlp_translate/llm_provider/__init__.py
easy_nlp_translate/llm_provider/anthropic.py
easy_nlp_translate/llm_provider/gemini.py
easy_nlp_translate/llm_provider/ollama.py
easy_nlp_translate/llm_provider/openai.py
easy_nlp_translate/prompts/__init__.py
easy_nlp_translate/prompts/custom_prompt.jinja
easy_nlp_translate/prompts/default_translation.jinja
easy_nlp_translate/prompts/formal_translate_and_summarize.jinja
easy_nlp_translate/prompts/formal_translation.jinja
easy_nlp_translate/prompts/poetic_translation.jinja
easy_nlp_translate/prompts/romantic_translation.jinja
easy_nlp_translate/prompts/translate_and_summarize.jinja
easy_nlp_translate-1.0.1.dist-info/licenses/LICENSE
easy_nlp_translate-1.0.1.dist-info/METADATA
easy_nlp_translate-1.0.1.dist-info/WHEEL
easy_nlp_translate-1.0.1.dist-info/top_level.txt
easy_nlp_translate-1.0.1.dist-info/RECORD
