Metadata-Version: 2.4
Name: easy-nlp-translate
Version: 1.0.1
Summary: Add your description here
Requires-Python: <=3.12,>=3.11
License-File: LICENSE
Requires-Dist: anthropic>=0.52.1
Requires-Dist: datasets>=3.6.0
Requires-Dist: evaluate>=0.4.3
Requires-Dist: google-genai>=1.16.1
Requires-Dist: huggingface>=0.0.1
Requires-Dist: langdetect>=1.0.9
Requires-Dist: matplotlib>=3.10.3
Requires-Dist: nltk>=3.9.1
Requires-Dist: ollama>=0.4.8
Requires-Dist: openai>=1.82.0
Requires-Dist: pandas>=2.2.3
Requires-Dist: protobuf>=6.31.0
Requires-Dist: python-dotenv>=1.1.0
Requires-Dist: pyyaml>=6.0.2
Requires-Dist: seaborn>=0.13.2
Requires-Dist: sentencepiece>=0.2.0
Requires-Dist: torch>=2.7.0
Requires-Dist: transformers>=4.51.3
Dynamic: license-file
